fast_hotels/__init__.py
fast_hotels/core.py
fast_hotels/fallback_playwright.py
fast_hotels/filter.py
fast_hotels/hotels_impl.py
fast_hotels/hotels_pb2.py
fast_hotels/local_playwright.py
fast_hotels/primp.py
fast_hotels/schema.py
fast_hotels/utils.py
fast_hotels-0.2.1.dist-info/licenses/LICENSE
tests/test_fast_hotels.py
fast_hotels-0.2.1.dist-info/METADATA
fast_hotels-0.2.1.dist-info/WHEEL
fast_hotels-0.2.1.dist-info/top_level.txt
fast_hotels-0.2.1.dist-info/RECORD
