Metadata-Version: 2.4
Name: fast-hotels
Version: 0.2.1
Summary: A fast, simple hotel scraper for Google Hotels, inspired by fast-flights.
Author-email: Jonathan Gan <jg.developor@gmail.com>
License: MIT License
Classifier: Programming Language :: Python :: 3
Classifier: License :: OSI Approved :: MIT License
Classifier: Operating System :: OS Independent
Requires-Python: >=3.8
License-File: LICENSE
Requires-Dist: playwright>=1.40.0
Requires-Dist: requests>=2.31.0
Dynamic: license-file
